GALINDA/GALINDA.py
GALINDA/__init__.py
GALINDA/tests/test_animate.py
GALINDA/tests/test_histogram.py
GALINDA/tests/test_import.py
GALINDA/tests/test_plot.py
galinda-1.0.3.dist-info/licenses/LICENSE
galinda-1.0.3.dist-info/METADATA
galinda-1.0.3.dist-info/WHEEL
galinda-1.0.3.dist-info/top_level.txt
galinda-1.0.3.dist-info/RECORD
